flox_bootstrap/__init__.py
flox_bootstrap/command.py
flox_bootstrap/configure.py
flox_bootstrap/project.py
flox_bootstrap-0.1.3.dist-info/entry_points.txt
flox_bootstrap-0.1.3.dist-info/WHEEL
flox_bootstrap-0.1.3.dist-info/METADATA
flox_bootstrap-0.1.3.dist-info/RECORD
