Metadata-Version: 2.1
Name: flox-bootstrap
Version: 0.1.3
Summary: Bootstrap your project with predefined templates
Home-page: https://github.com/getflox/flox-bootstrap
License: MIT
Author: Michal Przytulski
Author-email: michal@przytulski.pl
Requires-Python: >=3.6.2,<4.0.0
Classifier: License :: OSI Approved :: MIT License
Classifier: Programming Language :: Python :: 3
Classifier: Programming Language :: Python :: 3.7
Classifier: Programming Language :: Python :: 3.8
Requires-Dist: click (>=7.0,<8.0)
Requires-Dist: flox-core (>=0.2,<1.0.0)
Requires-Dist: jinja2 (>=2.11,<3.0)
Requires-Dist: stringcase (>=1.2,<2.0)
